nats_tui/__init__.py
nats_tui/__main__.py
nats_tui/adapter.py
nats_tui/app.py
nats_tui/app.tcss
nats_tui/app_base.py
nats_tui/cli.py
nats_tui/colors.py
nats_tui/config.py
nats_tui/exception.py
nats_tui/global.tcss
nats_tui/keymap.py
nats_tui/messages.py
nats_tui/components/__init__.py
nats_tui/components/confirm_bar.py
nats_tui/components/confirm_dialog.py
nats_tui/components/connection_dialog.py
nats_tui/components/consumer_detail.py
nats_tui/components/consumer_list.py
nats_tui/components/create_consumer_dialog.py
nats_tui/components/create_kv_dialog.py
nats_tui/components/create_object_store_dialog.py
nats_tui/components/create_stream_dialog.py
nats_tui/components/help_screen.py
nats_tui/components/kv_bucket_list.py
nats_tui/components/kv_key_list.py
nats_tui/components/kv_put_dialog.py
nats_tui/components/kv_value_detail.py
nats_tui/components/message_detail.py
nats_tui/components/message_list.py
nats_tui/components/object_detail.py
nats_tui/components/object_list.py
nats_tui/components/object_put_dialog.py
nats_tui/components/object_store_list.py
nats_tui/components/publish_dialog.py
nats_tui/components/status_bar.py
nats_tui/components/stream_detail.py
nats_tui/components/stream_list.py
nats_tui/components/stream_message_detail.py
nats_tui/components/stream_message_list.py
nats_tui/components/subject_details.py
nats_tui/components/subject_tree.py
nats_tui/components/subscribe_dialog.py
nats_tui-0.3.0.dist-info/METADATA
nats_tui-0.3.0.dist-info/WHEEL
nats_tui-0.3.0.dist-info/entry_points.txt
nats_tui-0.3.0.dist-info/RECORD
