Metadata-Version: 2.4
Name: nats-tui
Version: 0.3.0
Summary: A terminal UI for NATS cluster management
Project-URL: Homepage, https://github.com/coreyellis/nats-tui
Project-URL: Repository, https://github.com/coreyellis/nats-tui
Project-URL: Issues, https://github.com/coreyellis/nats-tui/issues
Author-email: Corey Ellis <corey@cmetech.io>
License-Expression: MIT
Keywords: jetstream,messaging,nats,terminal,textual,tui
Classifier: Development Status :: 4 - Beta
Classifier: Environment :: Console
Classifier: Intended Audience :: Developers
Classifier: Intended Audience :: System Administrators
Classifier: License :: OSI Approved :: MIT License
Classifier: Operating System :: OS Independent
Classifier: Programming Language :: Python :: 3
Classifier: Programming Language :: Python :: 3.10
Classifier: Programming Language :: Python :: 3.11
Classifier: Programming Language :: Python :: 3.12
Classifier: Programming Language :: Python :: 3.13
Classifier: Topic :: System :: Systems Administration
Classifier: Topic :: Utilities
Classifier: Typing :: Typed
Requires-Python: >=3.10
Requires-Dist: nats-py>=2.0.0
Requires-Dist: platformdirs>=4.0.0
Requires-Dist: rich-click>=1.9.0
Requires-Dist: textual>=0.47.0
Requires-Dist: tomlkit>=0.12.0
Provides-Extra: dev
Requires-Dist: pytest-asyncio>=0.23.0; extra == 'dev'
Requires-Dist: pytest>=8.0.0; extra == 'dev'
